setup.py
cache/__init__.py
cache/admin.py
cache/constants.py
cache/listeners.py
cache/manager.py
cache/models.py
cache/service.py
cache/shortcuts.py
cache/tests.py
cache/migrations/0001_initial.py
cache/migrations/__init__.py
django_caching.egg-info/PKG-INFO
django_caching.egg-info/SOURCES.txt
django_caching.egg-info/dependency_links.txt
django_caching.egg-info/requires.txt
django_caching.egg-info/top_level.txt